scons_tool_cxxtest-0.2.5-py3.8-nspkg.pth
sconstool/cxxtest/__init__.py
sconstool/cxxtest/about.py
scons_tool_cxxtest-0.2.5.dist-info/METADATA
scons_tool_cxxtest-0.2.5.dist-info/WHEEL
scons_tool_cxxtest-0.2.5.dist-info/namespace_packages.txt
scons_tool_cxxtest-0.2.5.dist-info/top_level.txt
scons_tool_cxxtest-0.2.5.dist-info/RECORD
