Metadata-Version: 2.1
Name: scons-tool-cxxtest
Version: 0.2.5
Summary: SCons tool to compile and run tests based on CxxTest framework
Home-page: https://github.com/ptomulik/scons-tool-cxxtest
Author: Paweł Tomulik
Author-email: ptomulik@meil.pw.edu.pl
License: UNKNOWN
Platform: UNKNOWN
Requires-Python: >=2.7
Requires-Dist: scons-tool-cxxtestgen (>=0.1.5)
Requires-Dist: scons-tool-util (>=0.1.9)
